stman/__init__.py
stman/cli.py
stman/commands.py
stman/dir_size.dll
stman/dir_utils.py
stman/display.py
stman/input_handler.py
stman/messages.py
stman/show_welcome.txt
stman/state.py
stman/ui_spinner.py
stman-0.1.0.dist-info/licenses/LICENSE
stman-0.1.0.dist-info/METADATA
stman-0.1.0.dist-info/WHEEL
stman-0.1.0.dist-info/entry_points.txt
stman-0.1.0.dist-info/top_level.txt
stman-0.1.0.dist-info/RECORD
