Metadata-Version: 2.4
Name: stman
Version: 0.1.0
Summary: A lightweight CLI tool that tabulates device/folder storage.
Author-email: Garrett Connell <glconnell.tx@gmail.com>
License: MIT
Project-URL: Homepage, https://github.com/glcon/storage-manager
Keywords: storage,disk,directory,size,cli,windows
Classifier: Development Status :: 4 - Beta
Classifier: Intended Audience :: End Users/Desktop
Classifier: License :: OSI Approved :: MIT License
Classifier: Operating System :: Microsoft :: Windows
Classifier: Programming Language :: Python :: 3
Classifier: Programming Language :: Python :: 3.8
Classifier: Programming Language :: Python :: 3.9
Classifier: Programming Language :: Python :: 3.10
Classifier: Programming Language :: Python :: 3.11
Classifier: Programming Language :: Python :: 3.12
Classifier: Topic :: System :: Filesystems
Classifier: Topic :: Utilities
Requires-Python: >=3.8
License-File: LICENSE
Requires-Dist: psutil
Requires-Dist: rich
Provides-Extra: windows
Dynamic: license-file
